LICENSE
pyhalomodel/__init__.py
pyhalomodel/camb_stuff.py
pyhalomodel/constants.py
pyhalomodel/cosmology.py
pyhalomodel/darkquest.py
pyhalomodel/pyhalomodel.py
pyhalomodel/utility.py
pyhalomodel-1.0.2.dist-info/LICENSE
pyhalomodel-1.0.2.dist-info/METADATA
pyhalomodel-1.0.2.dist-info/WHEEL
pyhalomodel-1.0.2.dist-info/RECORD
