Metadata-Version: 2.1
Name: pyhalomodel
Version: 1.0.2
Summary: Halo model power spectrum calculations
Home-page: https://github.com/alexander-mead/pyhalomodel
License: MIT
Keywords: cosmology,halo model,dark matter,dark energy,galaxies
Author: Alexander Mead
Author-email: alexander.j.mead@googlemail.com
Requires-Python: >=3.9,<3.13
Classifier: License :: OSI Approved :: MIT License
Classifier: Programming Language :: Python :: 3
Classifier: Programming Language :: Python :: 3.9
Classifier: Programming Language :: Python :: 3.10
Classifier: Programming Language :: Python :: 3.11
Classifier: Programming Language :: Python :: 3.12
Requires-Dist: numpy (>=1.24.1,<2.0.0)
Requires-Dist: scipy (>=1.10.0,<2.0.0)
Project-URL: Repository, https://github.com/alexander-mead/pyhalomodel
